streamlit_page_link_params/__init__.py
streamlit_page_link_params/page_link_ex.py
streamlit_page_link_params-0.3.3.dist-info/LICENSE
streamlit_page_link_params-0.3.3.dist-info/METADATA
streamlit_page_link_params-0.3.3.dist-info/WHEEL
streamlit_page_link_params-0.3.3.dist-info/top_level.txt
streamlit_page_link_params-0.3.3.dist-info/RECORD
