Metadata-Version: 2.1
Name: streamlit-page-link-params
Version: 0.3.3
Summary: An alternative to the official Streamlit page_link component that supports query parameters.
Author-email: Tongshengzhou <tongshengzhou@gmail.com>
License: Copyright (c) 2018-2021 Streamlit Inc.
Project-URL: Homepage, https://github.com/dancingpeanut/streamlit-page-link-params
Project-URL: Repository, https://github.com/dancingpeanut/streamlit-page-link-params
Classifier: Programming Language :: Python :: Implementation :: CPython
Requires-Python: >=3.8
License-File: LICENSE
Requires-Dist: streamlit >=1.37
Requires-Dist: streamlit-event-hook >=0.3
Requires-Dist: streamlit-js-callback >=1.0
